[{"received": false, "loading": false, "table_name": "condition_occurrence", "hpo_id": "va", "log_id": "2017-05-06 17:17:59.383000", "file_name": "va_condition_occurrence_datasprint_2.csv", "message": "File not found", "parsing": false}, {"received": false, "loading": false, "table_name": "visit_occurrence", "hpo_id": "va", "log_id": "2017-05-06 17:17:59.450000", "file_name": "va_visit_occurrence_datasprint_2.csv", "message": "File not found", "parsing": false}, {"received": false, "loading": false, "table_name": "procedure_occurrence", "hpo_id": "va", "log_id": "2017-05-06 17:17:59.440000", "file_name": "va_procedure_occurrence_datasprint_2.csv", "message": "File not found", "parsing": false}, {"received": false, "loading": false, "table_name": "person", "hpo_id": "va", "log_id": "2017-05-06 17:17:59.427000", "file_name": "va_person_datasprint_2.csv", "message": "File not found", "parsing": false}, {"received": false, "loading": false, "table_name": "measurement", "hpo_id": "va", "log_id": "2017-05-06 17:17:59.413000", "file_name": "va_measurement_datasprint_2.csv", "message": "File not found", "parsing": false}, {"received": false, "loading": false, "table_name": "drug_exposure", "hpo_id": "va", "log_id": "2017-05-06 17:17:59.400000", "file_name": "va_drug_exposure_datasprint_2.csv", "message": "File not found", "parsing": false}, {"received": true, "loading": true, "table_name": "condition_occurrence", "hpo_id": "jhchc", "log_id": "2017-05-06 16:51:00.953000", "file_name": "jhchc_condition_occurrence_datasprint_2.csv", "message": null, "parsing": true}, {"received": true, "loading": true, "table_name": "visit_occurrence", "hpo_id": "jhchc", "log_id": "2017-05-06 16:51:13.923000", "file_name": "jhchc_visit_occurrence_datasprint_2.csv", "message": null, "parsing": true}, {"received": true, "loading": true, "table_name": "procedure_occurrence", "hpo_id": "jhchc", "log_id": "2017-05-06 16:51:12.720000", "file_name": "jhchc_procedure_occurrence_datasprint_2.csv", "message": null, "parsing": true}, {"received": true, "loading": true, "table_name": "person", "hpo_id": "jhchc", "log_id": "2017-05-06 16:51:11.450000", "file_name": "jhchc_person_datasprint_2.csv", "message": null, "parsing": true}, {"received": true, "loading": true, "table_name": "measurement", "hpo_id": "jhchc", "log_id": "2017-05-06 16:51:11.040000", "file_name": "jhchc_measurement_datasprint_2.csv", "message": null, "parsing": true}, {"received": true, "loading": true, "table_name": "drug_exposure", "hpo_id": "jhchc", "log_id": "2017-05-06 16:51:02.927000", "file_name": "jhchc_drug_exposure_datasprint_2.csv", "message": null, "parsing": true}, {"received": false, "loading": false, "table_name": "condition_occurrence", "hpo_id": "cpmc_usc", "log_id": "2017-05-06 16:07:27.173000", "file_name": "cpmc_usc_condition_occurrence_datasprint_2.csv", "message": "File not found", "parsing": false}, {"received": false, "loading": false, "table_name": "visit_occurrence", "hpo_id": "cpmc_usc", "log_id": "2017-05-06 16:07:27.243000", "file_name": "cpmc_usc_visit_occurrence_datasprint_2.csv", "message": "File not found", "parsing": false}, {"received": false, "loading": false, "table_name": "procedure_occurrence", "hpo_id": "cpmc_usc", "log_id": "2017-05-06 16:07:27.230000", "file_name": "cpmc_usc_procedure_occurrence_datasprint_2.csv", "message": "File not found", "parsing": false}, {"received": false, "loading": false, "table_name": "person", "hpo_id": "cpmc_usc", "log_id": "2017-05-06 16:07:27.217000", "file_name": "cpmc_usc_person_datasprint_2.csv", "message": "File not found", "parsing": false}, {"received": false, "loading": false, "table_name": "measurement", "hpo_id": "cpmc_usc", "log_id": "2017-05-06 16:07:27.207000", "file_name": "cpmc_usc_measurement_datasprint_2.csv", "message": "File not found", "parsing": false}, {"received": false, "loading": false, "table_name": "drug_exposure", "hpo_id": "cpmc_usc", "log_id": "2017-05-06 16:07:27.193000", "file_name": "cpmc_usc_drug_exposure_datasprint_2.csv", "message": "File not found", "parsing": false}, {"received": true, "loading": true, "table_name": "condition_occurrence", "hpo_id": "chci", "log_id": "2017-05-06 16:02:23.233000", "file_name": "chci_condition_occurrence_datasprint_2.csv", "message": null, "parsing": true}, {"received": true, "loading": true, "table_name": "visit_occurrence", "hpo_id": "chci", "log_id": "2017-05-06 16:02:28.890000", "file_name": "chci_visit_occurrence_datasprint_2.csv", "message": null, "parsing": true}, {"received": true, "loading": true, "table_name": "procedure_occurrence", "hpo_id": "chci", "log_id": "2017-05-06 16:02:28.207000", "file_name": "chci_procedure_occurrence_datasprint_2.csv", "message": null, "parsing": true}, {"received": true, "loading": true, "table_name": "person", "hpo_id": "chci", "log_id": "2017-05-06 16:02:27.347000", "file_name": "chci_person_datasprint_2.csv", "message": null, "parsing": true}, {"received": true, "loading": true, "table_name": "measurement", "hpo_id": "chci", "log_id": "2017-05-06 16:02:26.933000", "file_name": "chci_measurement_datasprint_2.csv", "message": null, "parsing": true}, {"received": true, "loading": true, "table_name": "drug_exposure", "hpo_id": "chci", "log_id": "2017-05-06 16:02:25.363000", "file_name": "chci_drug_exposure_datasprint_2.csv", "message": null, "parsing": true}, {"received": true, "loading": true, "table_name": "condition_occurrence", "hpo_id": "uamc_uofa", "log_id": "2017-05-06 17:15:08.550000", "file_name": "uamc_uofa_condition_occurrence_datasprint_2.csv", "message": null, "parsing": true}, {"received": true, "loading": true, "table_name": "visit_occurrence", "hpo_id": "uamc_uofa", "log_id": "2017-05-06 17:17:33.353000", "file_name": "uamc_uofa_visit_occurrence_datasprint_2.csv", "message": null, "parsing": true}, {"received": true, "loading": true, "table_name": "procedure_occurrence", "hpo_id": "uamc_uofa", "log_id": "2017-05-06 17:17:31.850000", "file_name": "uamc_uofa_procedure_occurrence_datasprint_2.csv", "message": null, "parsing": true}, {"received": true, "loading": true, "table_name": "person", "hpo_id": "uamc_uofa", "log_id": "2017-05-06 17:17:21", "file_name": "uamc_uofa_person_datasprint_2.csv", "message": null, "parsing": true}, {"received": true, "loading": true, "table_name": "measurement", "hpo_id": "uamc_uofa", "log_id": "2017-05-06 17:17:20.587000", "file_name": "uamc_uofa_measurement_datasprint_2.csv", "message": null, "parsing": true}, {"received": true, "loading": true, "table_name": "drug_exposure", "hpo_id": "uamc_uofa", "log_id": "2017-05-06 17:15:09.067000", "file_name": "uamc_uofa_drug_exposure_datasprint_2.csv", "message": null, "parsing": true}, {"received": false, "loading": false, "table_name": "condition_occurrence", "hpo_id": "cpmc_ceders", "log_id": "2017-05-06 16:04:42.597000", "file_name": "cpmc_ceders_condition_occurrence_datasprint_2.csv", "message": "File not found", "parsing": false}, {"received": false, "loading": false, "table_name": "visit_occurrence", "hpo_id": "cpmc_ceders", "log_id": "2017-05-06 16:04:42.660000", "file_name": "cpmc_ceders_visit_occurrence_datasprint_2.csv", "message": "File not found", "parsing": false}, {"received": false, "loading": false, "table_name": "procedure_occurrence", "hpo_id": "cpmc_ceders", "log_id": "2017-05-06 16:04:42.650000", "file_name": "cpmc_ceders_procedure_occurrence_datasprint_2.csv", "message": "File not found", "parsing": false}, {"received": false, "loading": false, "table_name": "person", "hpo_id": "cpmc_ceders", "log_id": "2017-05-06 16:04:42.637000", "file_name": "cpmc_ceders_person_datasprint_2.csv", "message": "File not found", "parsing": false}, {"received": false, "loading": false, "table_name": "measurement", "hpo_id": "cpmc_ceders", "log_id": "2017-05-06 16:04:42.623000", "file_name": "cpmc_ceders_measurement_datasprint_2.csv", "message": "File not found", "parsing": false}, {"received": false, "loading": false, "table_name": "drug_exposure", "hpo_id": "cpmc_ceders", "log_id": "2017-05-06 16:04:42.613000", "file_name": "cpmc_ceders_drug_exposure_datasprint_2.csv", "message": "File not found", "parsing": false}, {"received": true, "loading": true, "table_name": "condition_occurrence", "hpo_id": "ipmc_northshore", "log_id": "2017-05-06 16:49:34.923000", "file_name": "ipmc_northshore_condition_occurrence_datasprint_2.csv", "message": null, "parsing": true}, {"received": true, "loading": false, "table_name": "visit_occurrence", "hpo_id": "ipmc_northshore", "log_id": "2017-05-06 16:49:37.477000", "file_name": "ipmc_northshore_visit_occurrence_datasprint_2.csv", "message": "Error tokenizing data. C error: EOF inside string starting at line 9444", "parsing": false}, {"received": true, "loading": true, "table_name": "procedure_occurrence", "hpo_id": "ipmc_northshore", "log_id": "2017-05-06 16:49:37.387000", "file_name": "ipmc_northshore_procedure_occurrence_datasprint_2.csv", "message": null, "parsing": true}, {"received": true, "loading": false, "table_name": "person", "hpo_id": "ipmc_northshore", "log_id": "2017-05-06 16:49:34.983000", "file_name": "ipmc_northshore_person_datasprint_2.csv", "message": "Error tokenizing data. C error: EOF inside string starting at line 101", "parsing": false}, {"received": false, "loading": false, "table_name": "measurement", "hpo_id": "ipmc_northshore", "log_id": "2017-05-06 16:49:34.950000", "file_name": "ipmc_northshore_measurement_datasprint_2.csv", "message": "File not found", "parsing": false}, {"received": false, "loading": false, "table_name": "drug_exposure", "hpo_id": "ipmc_northshore", "log_id": "2017-05-06 16:49:34.937000", "file_name": "ipmc_northshore_drug_exposure_datasprint_2.csv", "message": "File not found", "parsing": false}, {"received": true, "loading": true, "table_name": "condition_occurrence", "hpo_id": "nyc_cu", "log_id": "2017-05-06 16:08:11.550000", "file_name": "nyc_cu_condition_occurrence_datasprint_2.csv", "message": null, "parsing": true}, {"received": true, "loading": true, "table_name": "visit_occurrence", "hpo_id": "nyc_cu", "log_id": "2017-05-06 16:16:25.187000", "file_name": "nyc_cu_visit_occurrence_datasprint_2.csv", "message": null, "parsing": true}, {"received": true, "loading": true, "table_name": "procedure_occurrence", "hpo_id": "nyc_cu", "log_id": "2017-05-06 16:16:20.007000", "file_name": "nyc_cu_procedure_occurrence_datasprint_2.csv", "message": null, "parsing": true}, {"received": true, "loading": true, "table_name": "person", "hpo_id": "nyc_cu", "log_id": "2017-05-06 16:16:16.183000", "file_name": "nyc_cu_person_datasprint_2.csv", "message": null, "parsing": true}, {"received": true, "loading": true, "table_name": "measurement", "hpo_id": "nyc_cu", "log_id": "2017-05-06 16:16:15.790000", "file_name": "nyc_cu_measurement_datasprint_2.csv", "message": null, "parsing": true}, {"received": true, "loading": true, "table_name": "drug_exposure", "hpo_id": "nyc_cu", "log_id": "2017-05-06 16:08:43.523000", "file_name": "nyc_cu_drug_exposure_datasprint_2.csv", "message": null, "parsing": true}, {"received": false, "loading": false, "table_name": "condition_occurrence", "hpo_id": "nec_bu", "log_id": "2017-05-06 16:51:57.430000", "file_name": "nec_bu_condition_occurrence_datasprint_2.csv", "message": "File not found", "parsing": false}, {"received": false, "loading": false, "table_name": "visit_occurrence", "hpo_id": "nec_bu", "log_id": "2017-05-06 16:51:57.490000", "file_name": "nec_bu_visit_occurrence_datasprint_2.csv", "message": "File not found", "parsing": false}, {"received": false, "loading": false, "table_name": "procedure_occurrence", "hpo_id": "nec_bu", "log_id": "2017-05-06 16:51:57.477000", "file_name": "nec_bu_procedure_occurrence_datasprint_2.csv", "message": "File not found", "parsing": false}, {"received": false, "loading": false, "table_name": "person", "hpo_id": "nec_bu", "log_id": "2017-05-06 16:51:57.467000", "file_name": "nec_bu_person_datasprint_2.csv", "message": "File not found", "parsing": false}, {"received": false, "loading": false, "table_name": "measurement", "hpo_id": "nec_bu", "log_id": "2017-05-06 16:51:57.457000", "file_name": "nec_bu_measurement_datasprint_2.csv", "message": "File not found", "parsing": false}, {"received": false, "loading": false, "table_name": "drug_exposure", "hpo_id": "nec_bu", "log_id": "2017-05-06 16:51:57.443000", "file_name": "nec_bu_drug_exposure_datasprint_2.csv", "message": "File not found", "parsing": false}, {"received": true, "loading": true, "table_name": "condition_occurrence", "hpo_id": "tach_hfhs", "log_id": "2017-05-06 17:08:26.393000", "file_name": "tach_hfhs_condition_occurrence_datasprint_2.csv", "message": null, "parsing": true}, {"received": true, "loading": true, "table_name": "visit_occurrence", "hpo_id": "tach_hfhs", "log_id": "2017-05-06 17:09:33.690000", "file_name": "tach_hfhs_visit_occurrence_datasprint_2.csv", "message": null, "parsing": true}, {"received": true, "loading": true, "table_name": "procedure_occurrence", "hpo_id": "tach_hfhs", "log_id": "2017-05-06 17:09:30.670000", "file_name": "tach_hfhs_procedure_occurrence_datasprint_2.csv", "message": null, "parsing": true}, {"received": true, "loading": true, "table_name": "person", "hpo_id": "tach_hfhs", "log_id": "2017-05-06 17:09:27.583000", "file_name": "tach_hfhs_person_datasprint_2.csv", "message": null, "parsing": true}, {"received": true, "loading": true, "table_name": "measurement", "hpo_id": "tach_hfhs", "log_id": "2017-05-06 17:09:27.190000", "file_name": "tach_hfhs_measurement_datasprint_2.csv", "message": null, "parsing": true}, {"received": true, "loading": true, "table_name": "drug_exposure", "hpo_id": "tach_hfhs", "log_id": "2017-05-06 17:08:41.777000", "file_name": "tach_hfhs_drug_exposure_datasprint_2.csv", "message": null, "parsing": true}, {"received": true, "loading": true, "table_name": "condition_occurrence", "hpo_id": "uamc_banner", "log_id": "2017-05-06 17:09:56.857000", "file_name": "uamc_banner_condition_occurrence_datasprint_2.csv", "message": null, "parsing": true}, {"received": true, "loading": true, "table_name": "visit_occurrence", "hpo_id": "uamc_banner", "log_id": "2017-05-06 17:14:22.637000", "file_name": "uamc_banner_visit_occurrence_datasprint_2.csv", "message": null, "parsing": true}, {"received": true, "loading": true, "table_name": "procedure_occurrence", "hpo_id": "uamc_banner", "log_id": "2017-05-06 17:14:21.640000", "file_name": "uamc_banner_procedure_occurrence_datasprint_2.csv", "message": null, "parsing": true}, {"received": true, "loading": true, "table_name": "person", "hpo_id": "uamc_banner", "log_id": "2017-05-06 17:14:18.397000", "file_name": "uamc_banner_person_datasprint_2.csv", "message": null, "parsing": true}, {"received": true, "loading": true, "table_name": "measurement", "hpo_id": "uamc_banner", "log_id": "2017-05-06 17:14:18.003000", "file_name": "uamc_banner_measurement_datasprint_2.csv", "message": null, "parsing": true}, {"received": true, "loading": true, "table_name": "drug_exposure", "hpo_id": "uamc_banner", "log_id": "2017-05-06 17:11:53.720000", "file_name": "uamc_banner_drug_exposure_datasprint_2.csv", "message": null, "parsing": true}, {"received": true, "loading": true, "table_name": "condition_occurrence", "hpo_id": "chs", "log_id": "2017-05-06 16:03:13.647000", "file_name": "chs_condition_occurrence_datasprint_2.csv", "message": null, "parsing": true}, {"received": true, "loading": true, "table_name": "visit_occurrence", "hpo_id": "chs", "log_id": "2017-05-06 16:04:16.107000", "file_name": "chs_visit_occurrence_datasprint_2.csv", "message": null, "parsing": true}, {"received": true, "loading": true, "table_name": "procedure_occurrence", "hpo_id": "chs", "log_id": "2017-05-06 16:04:04.380000", "file_name": "chs_procedure_occurrence_datasprint_2.csv", "message": null, "parsing": true}, {"received": true, "loading": true, "table_name": "person", "hpo_id": "chs", "log_id": "2017-05-06 16:03:54.557000", "file_name": "chs_person_datasprint_2.csv", "message": null, "parsing": true}, {"received": true, "loading": true, "table_name": "measurement", "hpo_id": "chs", "log_id": "2017-05-06 16:03:54.153000", "file_name": "chs_measurement_datasprint_2.csv", "message": null, "parsing": true}, {"received": true, "loading": true, "table_name": "drug_exposure", "hpo_id": "chs", "log_id": "2017-05-06 16:03:25.037000", "file_name": "chs_drug_exposure_datasprint_2.csv", "message": null, "parsing": true}, {"received": true, "loading": false, "table_name": "condition_occurrence", "hpo_id": "cpmc_uc", "log_id": "2017-05-06 16:05:19.560000", "file_name": "cpmc_uc_condition_occurrence_datasprint_2.csv", "message": "(pymssql.OperationalError) (241, 'Conversion failed when converting date and/or time from character string.DB-Lib error message 20018, severity 16:\\nGeneral SQL Server error: Check messages from the SQL Server\\n')", "parsing": true}, {"received": true, "loading": false, "table_name": "visit_occurrence", "hpo_id": "cpmc_uc", "log_id": "2017-05-06 16:07:01.457000", "file_name": "cpmc_uc_visit_occurrence_datasprint_2.csv", "message": "(pymssql.IntegrityError) (515, \"Cannot insert the value NULL into column 'visit_end_date', table 'pmi_sprints.cpmc_uc.visit_occurrence'; column does not allow nulls. INSERT fails.DB-Lib error message 20018, severity 16:\\nGeneral SQL Server error: Check messages from the SQL Server\\n\")", "parsing": true}, {"received": true, "loading": true, "table_name": "procedure_occurrence", "hpo_id": "cpmc_uc", "log_id": "2017-05-06 16:06:58.530000", "file_name": "cpmc_uc_procedure_occurrence_datasprint_2.csv", "message": null, "parsing": true}, {"received": true, "loading": false, "table_name": "person", "hpo_id": "cpmc_uc", "log_id": "2017-05-06 16:06:30.867000", "file_name": "cpmc_uc_person_datasprint_2.csv", "message": "(pymssql.OperationalError) (8114, 'Error converting data type varchar to bigint.DB-Lib error message 20018, severity 16:\\nGeneral SQL Server error: Check messages from the SQL Server\\n')", "parsing": true}, {"received": true, "loading": true, "table_name": "measurement", "hpo_id": "cpmc_uc", "log_id": "2017-05-06 16:06:30.780000", "file_name": "cpmc_uc_measurement_datasprint_2.csv", "message": null, "parsing": true}, {"received": true, "loading": true, "table_name": "drug_exposure", "hpo_id": "cpmc_uc", "log_id": "2017-05-06 16:05:41.397000", "file_name": "cpmc_uc_drug_exposure_datasprint_2.csv", "message": null, "parsing": true}, {"received": true, "loading": true, "table_name": "condition_occurrence", "hpo_id": "nyc_cornell", "log_id": "2017-05-06 16:18:56.713000", "file_name": "nyc_cornell_condition_occurrence_datasprint_2.csv", "message": null, "parsing": true}, {"received": true, "loading": true, "table_name": "visit_occurrence", "hpo_id": "nyc_cornell", "log_id": "2017-05-06 16:21:58.147000", "file_name": "nyc_cornell_visit_occurrence_datasprint_2.csv", "message": null, "parsing": true}, {"received": true, "loading": true, "table_name": "procedure_occurrence", "hpo_id": "nyc_cornell", "log_id": "2017-05-06 16:20:03.403000", "file_name": "nyc_cornell_procedure_occurrence_datasprint_2.csv", "message": null, "parsing": true}, {"received": true, "loading": true, "table_name": "person", "hpo_id": "nyc_cornell", "log_id": "2017-05-06 16:18:58.927000", "file_name": "nyc_cornell_person_datasprint_2.csv", "message": null, "parsing": true}, {"received": true, "loading": false, "table_name": "measurement", "hpo_id": "nyc_cornell", "log_id": "2017-05-06 16:18:58.530000", "file_name": "nyc_cornell_measurement_datasprint_2.csv", "message": "Error tokenizing data. C error: Expected 18 fields in line 312615, saw 35\n", "parsing": false}, {"received": true, "loading": false, "table_name": "drug_exposure", "hpo_id": "nyc_cornell", "log_id": "2017-05-06 16:18:57.093000", "file_name": "nyc_cornell_drug_exposure_datasprint_2.csv", "message": "(pymssql.OperationalError) (8114, 'Error converting data type varchar to float.DB-Lib error message 20018, severity 16:\\nGeneral SQL Server error: Check messages from the SQL Server\\n')", "parsing": true}, {"received": true, "loading": true, "table_name": "condition_occurrence", "hpo_id": "syhc", "log_id": "2017-05-06 17:06:00.927000", "file_name": "syhc_condition_occurrence_datasprint_2.csv", "message": null, "parsing": true}, {"received": true, "loading": true, "table_name": "visit_occurrence", "hpo_id": "syhc", "log_id": "2017-05-06 17:07:53.690000", "file_name": "syhc_visit_occurrence_datasprint_2.csv", "message": null, "parsing": true}, {"received": true, "loading": true, "table_name": "procedure_occurrence", "hpo_id": "syhc", "log_id": "2017-05-06 17:07:53.293000", "file_name": "syhc_procedure_occurrence_datasprint_2.csv", "message": null, "parsing": true}, {"received": true, "loading": true, "table_name": "person", "hpo_id": "syhc", "log_id": "2017-05-06 17:07:52.887000", "file_name": "syhc_person_datasprint_2.csv", "message": null, "parsing": true}, {"received": true, "loading": true, "table_name": "measurement", "hpo_id": "syhc", "log_id": "2017-05-06 17:07:52.473000", "file_name": "syhc_measurement_datasprint_2.csv", "message": null, "parsing": true}, {"received": true, "loading": true, "table_name": "drug_exposure", "hpo_id": "syhc", "log_id": "2017-05-06 17:06:02.653000", "file_name": "syhc_drug_exposure_datasprint_2.csv", "message": null, "parsing": true}, {"received": true, "loading": false, "table_name": "condition_occurrence", "hpo_id": "ipmc_rush", "log_id": "2017-05-06 16:50:04.070000", "file_name": "ipmc_rush_condition_occurrence_datasprint_2.csv", "message": "(pymssql.OperationalError) (241, 'Conversion failed when converting date and/or time from character string.DB-Lib error message 20018, severity 16:\\nGeneral SQL Server error: Check messages from the SQL Server\\n')", "parsing": true}, {"received": true, "loading": true, "table_name": "visit_occurrence", "hpo_id": "ipmc_rush", "log_id": "2017-05-06 16:50:04.963000", "file_name": "ipmc_rush_visit_occurrence_datasprint_2.csv", "message": null, "parsing": true}, {"received": false, "loading": false, "table_name": "procedure_occurrence", "hpo_id": "ipmc_rush", "log_id": "2017-05-06 16:50:04.543000", "file_name": "ipmc_rush_procedure_occurrence_datasprint_2.csv", "message": "File not found", "parsing": false}, {"received": true, "loading": true, "table_name": "person", "hpo_id": "ipmc_rush", "log_id": "2017-05-06 16:50:04.530000", "file_name": "ipmc_rush_person_datasprint_2.csv", "message": null, "parsing": true}, {"received": false, "loading": false, "table_name": "measurement", "hpo_id": "ipmc_rush", "log_id": "2017-05-06 16:50:04.100000", "file_name": "ipmc_rush_measurement_datasprint_2.csv", "message": "File not found", "parsing": false}, {"received": false, "loading": false, "table_name": "drug_exposure", "hpo_id": "ipmc_rush", "log_id": "2017-05-06 16:50:04.087000", "file_name": "ipmc_rush_drug_exposure_datasprint_2.csv", "message": "File not found", "parsing": false}, {"received": true, "loading": true, "table_name": "condition_occurrence", "hpo_id": "hrhc", "log_id": "2017-05-06 16:35:50.513000", "file_name": "hrhc_condition_occurrence_datasprint_2.csv", "message": null, "parsing": true}, {"received": true, "loading": true, "table_name": "visit_occurrence", "hpo_id": "hrhc", "log_id": "2017-05-06 16:35:57.683000", "file_name": "hrhc_visit_occurrence_datasprint_2.csv", "message": null, "parsing": true}, {"received": true, "loading": true, "table_name": "procedure_occurrence", "hpo_id": "hrhc", "log_id": "2017-05-06 16:35:56.633000", "file_name": "hrhc_procedure_occurrence_datasprint_2.csv", "message": null, "parsing": true}, {"received": true, "loading": true, "table_name": "person", "hpo_id": "hrhc", "log_id": "2017-05-06 16:35:55.093000", "file_name": "hrhc_person_datasprint_2.csv", "message": null, "parsing": true}, {"received": true, "loading": false, "table_name": "measurement", "hpo_id": "hrhc", "log_id": "2017-05-06 16:35:54.680000", "file_name": "hrhc_measurement_datasprint_2.csv", "message": "(pymssql.OperationalError) (8114, 'Error converting data type varchar to float.DB-Lib error message 20018, severity 16:\\nGeneral SQL Server error: Check messages from the SQL Server\\n')", "parsing": true}, {"received": true, "loading": true, "table_name": "drug_exposure", "hpo_id": "hrhc", "log_id": "2017-05-06 16:35:53.617000", "file_name": "hrhc_drug_exposure_datasprint_2.csv", "message": null, "parsing": true}, {"received": true, "loading": true, "table_name": "condition_occurrence", "hpo_id": "ipmc_uchicago", "log_id": "2017-05-06 16:45:38.347000", "file_name": "ipmc_uchicago_condition_occurrence_datasprint_2.csv", "message": null, "parsing": true}, {"received": true, "loading": true, "table_name": "visit_occurrence", "hpo_id": "ipmc_uchicago", "log_id": "2017-05-06 16:48:32.313000", "file_name": "ipmc_uchicago_visit_occurrence_datasprint_2.csv", "message": null, "parsing": true}, {"received": true, "loading": true, "table_name": "procedure_occurrence", "hpo_id": "ipmc_uchicago", "log_id": "2017-05-06 16:48:12.537000", "file_name": "ipmc_uchicago_procedure_occurrence_datasprint_2.csv", "message": null, "parsing": true}, {"received": true, "loading": true, "table_name": "person", "hpo_id": "ipmc_uchicago", "log_id": "2017-05-06 16:45:38.777000", "file_name": "ipmc_uchicago_person_datasprint_2.csv", "message": null, "parsing": true}, {"received": false, "loading": false, "table_name": "measurement", "hpo_id": "ipmc_uchicago", "log_id": "2017-05-06 16:45:38.377000", "file_name": "ipmc_uchicago_measurement_datasprint_2.csv", "message": "File not found", "parsing": false}, {"received": false, "loading": false, "table_name": "drug_exposure", "hpo_id": "ipmc_uchicago", "log_id": "2017-05-06 16:45:38.360000", "file_name": "ipmc_uchicago_drug_exposure_datasprint_2.csv", "message": "File not found", "parsing": false}, {"received": true, "loading": true, "table_name": "condition_occurrence", "hpo_id": "ecchc", "log_id": "2017-05-06 16:22:48.177000", "file_name": "ecchc_condition_occurrence_datasprint_2.csv", "message": null, "parsing": true}, {"received": true, "loading": true, "table_name": "visit_occurrence", "hpo_id": "ecchc", "log_id": "2017-05-06 16:23:00.880000", "file_name": "ecchc_visit_occurrence_datasprint_2.csv", "message": null, "parsing": true}, {"received": true, "loading": false, "table_name": "procedure_occurrence", "hpo_id": "ecchc", "log_id": "2017-05-06 16:22:51.947000", "file_name": "ecchc_procedure_occurrence_datasprint_2.csv", "message": "(pymssql.OperationalError) (8114, 'Error converting data type varchar to bigint.DB-Lib error message 20018, severity 16:\\nGeneral SQL Server error: Check messages from the SQL Server\\n')", "parsing": true}, {"received": true, "loading": true, "table_name": "person", "hpo_id": "ecchc", "log_id": "2017-05-06 16:22:48.610000", "file_name": "ecchc_person_datasprint_2.csv", "message": null, "parsing": true}, {"received": false, "loading": false, "table_name": "measurement", "hpo_id": "ecchc", "log_id": "2017-05-06 16:22:48.207000", "file_name": "ecchc_measurement_datasprint_2.csv", "message": "File not found", "parsing": false}, {"received": false, "loading": false, "table_name": "drug_exposure", "hpo_id": "ecchc", "log_id": "2017-05-06 16:22:48.190000", "file_name": "ecchc_drug_exposure_datasprint_2.csv", "message": "File not found", "parsing": false}, {"received": false, "loading": false, "table_name": "condition_occurrence", "hpo_id": "nyc_hh", "log_id": "2017-05-06 16:22:21.427000", "file_name": "nyc_hh_condition_occurrence_datasprint_2.csv", "message": "File not found", "parsing": false}, {"received": false, "loading": false, "table_name": "visit_occurrence", "hpo_id": "nyc_hh", "log_id": "2017-05-06 16:22:21.497000", "file_name": "nyc_hh_visit_occurrence_datasprint_2.csv", "message": "File not found", "parsing": false}, {"received": false, "loading": false, "table_name": "procedure_occurrence", "hpo_id": "nyc_hh", "log_id": "2017-05-06 16:22:21.483000", "file_name": "nyc_hh_procedure_occurrence_datasprint_2.csv", "message": "File not found", "parsing": false}, {"received": false, "loading": false, "table_name": "person", "hpo_id": "nyc_hh", "log_id": "2017-05-06 16:22:21.470000", "file_name": "nyc_hh_person_datasprint_2.csv", "message": "File not found", "parsing": false}, {"received": false, "loading": false, "table_name": "measurement", "hpo_id": "nyc_hh", "log_id": "2017-05-06 16:22:21.457000", "file_name": "nyc_hh_measurement_datasprint_2.csv", "message": "File not found", "parsing": false}, {"received": false, "loading": false, "table_name": "drug_exposure", "hpo_id": "nyc_hh", "log_id": "2017-05-06 16:22:21.447000", "file_name": "nyc_hh_drug_exposure_datasprint_2.csv", "message": "File not found", "parsing": false}, {"received": true, "loading": true, "table_name": "condition_occurrence", "hpo_id": "ipmc_nu", "log_id": "2017-05-06 16:38:04.057000", "file_name": "ipmc_nu_condition_occurrence_datasprint_2.csv", "message": null, "parsing": true}, {"received": true, "loading": true, "table_name": "visit_occurrence", "hpo_id": "ipmc_nu", "log_id": "2017-05-06 16:44:19.880000", "file_name": "ipmc_nu_visit_occurrence_datasprint_2.csv", "message": null, "parsing": true}, {"received": true, "loading": true, "table_name": "procedure_occurrence", "hpo_id": "ipmc_nu", "log_id": "2017-05-06 16:43:58.917000", "file_name": "ipmc_nu_procedure_occurrence_datasprint_2.csv", "message": null, "parsing": true}, {"received": true, "loading": true, "table_name": "person", "hpo_id": "ipmc_nu", "log_id": "2017-05-06 16:43:52.157000", "file_name": "ipmc_nu_person_datasprint_2.csv", "message": null, "parsing": true}, {"received": true, "loading": true, "table_name": "measurement", "hpo_id": "ipmc_nu", "log_id": "2017-05-06 16:43:51.760000", "file_name": "ipmc_nu_measurement_datasprint_2.csv", "message": null, "parsing": true}, {"received": true, "loading": true, "table_name": "drug_exposure", "hpo_id": "ipmc_nu", "log_id": "2017-05-06 16:39:34.443000", "file_name": "ipmc_nu_drug_exposure_datasprint_2.csv", "message": null, "parsing": true}, {"received": true, "loading": true, "table_name": "condition_occurrence", "hpo_id": "ghs", "log_id": "2017-05-06 16:24:11.763000", "file_name": "ghs_condition_occurrence_datasprint_2.csv", "message": null, "parsing": true}, {"received": true, "loading": true, "table_name": "visit_occurrence", "hpo_id": "ghs", "log_id": "2017-05-06 16:35:27.187000", "file_name": "ghs_visit_occurrence_datasprint_2.csv", "message": null, "parsing": true}, {"received": true, "loading": true, "table_name": "procedure_occurrence", "hpo_id": "ghs", "log_id": "2017-05-06 16:34:52.600000", "file_name": "ghs_procedure_occurrence_datasprint_2.csv", "message": null, "parsing": true}, {"received": true, "loading": true, "table_name": "person", "hpo_id": "ghs", "log_id": "2017-05-06 16:32:45.980000", "file_name": "ghs_person_datasprint_2.csv", "message": null, "parsing": true}, {"received": true, "loading": true, "table_name": "measurement", "hpo_id": "ghs", "log_id": "2017-05-06 16:32:45.567000", "file_name": "ghs_measurement_datasprint_2.csv", "message": null, "parsing": true}, {"received": true, "loading": true, "table_name": "drug_exposure", "hpo_id": "ghs", "log_id": "2017-05-06 16:27:00.913000", "file_name": "ghs_drug_exposure_datasprint_2.csv", "message": null, "parsing": true}, {"received": true, "loading": true, "table_name": "condition_occurrence", "hpo_id": "pitt", "log_id": "2017-05-06 16:55:40.307000", "file_name": "pitt_condition_occurrence_datasprint_2.csv", "message": null, "parsing": true}, {"received": true, "loading": true, "table_name": "visit_occurrence", "hpo_id": "pitt", "log_id": "2017-05-06 17:05:36.817000", "file_name": "pitt_visit_occurrence_datasprint_2.csv", "message": null, "parsing": true}, {"received": true, "loading": true, "table_name": "procedure_occurrence", "hpo_id": "pitt", "log_id": "2017-05-06 17:04:16.307000", "file_name": "pitt_procedure_occurrence_datasprint_2.csv", "message": null, "parsing": true}, {"received": true, "loading": true, "table_name": "person", "hpo_id": "pitt", "log_id": "2017-05-06 17:04:01.330000", "file_name": "pitt_person_datasprint_2.csv", "message": null, "parsing": true}, {"received": true, "loading": true, "table_name": "measurement", "hpo_id": "pitt", "log_id": "2017-05-06 17:04:00.923000", "file_name": "pitt_measurement_datasprint_2.csv", "message": null, "parsing": true}, {"received": true, "loading": true, "table_name": "drug_exposure", "hpo_id": "pitt", "log_id": "2017-05-06 16:58:35.950000", "file_name": "pitt_drug_exposure_datasprint_2.csv", "message": null, "parsing": true}, {"received": false, "loading": false, "table_name": "condition_occurrence", "hpo_id": "ipmc_uic", "log_id": "2017-05-06 16:50:31.717000", "file_name": "ipmc_uic_condition_occurrence_datasprint_2.csv", "message": "File not found", "parsing": false}, {"received": false, "loading": false, "table_name": "visit_occurrence", "hpo_id": "ipmc_uic", "log_id": "2017-05-06 16:50:31.783000", "file_name": "ipmc_uic_visit_occurrence_datasprint_2.csv", "message": "File not found", "parsing": false}, {"received": false, "loading": false, "table_name": "procedure_occurrence", "hpo_id": "ipmc_uic", "log_id": "2017-05-06 16:50:31.770000", "file_name": "ipmc_uic_procedure_occurrence_datasprint_2.csv", "message": "File not found", "parsing": false}, {"received": false, "loading": false, "table_name": "person", "hpo_id": "ipmc_uic", "log_id": "2017-05-06 16:50:31.757000", "file_name": "ipmc_uic_person_datasprint_2.csv", "message": "File not found", "parsing": false}, {"received": false, "loading": false, "table_name": "measurement", "hpo_id": "ipmc_uic", "log_id": "2017-05-06 16:50:31.747000", "file_name": "ipmc_uic_measurement_datasprint_2.csv", "message": "File not found", "parsing": false}, {"received": false, "loading": false, "table_name": "drug_exposure", "hpo_id": "ipmc_uic", "log_id": "2017-05-06 16:50:31.733000", "file_name": "ipmc_uic_drug_exposure_datasprint_2.csv", "message": "File not found", "parsing": false}, {"received": true, "loading": true, "table_name": "condition_occurrence", "hpo_id": "nec_phs", "log_id": "2017-05-06 16:52:55.787000", "file_name": "nec_phs_condition_occurrence_datasprint_2.csv", "message": null, "parsing": true}, {"received": true, "loading": true, "table_name": "visit_occurrence", "hpo_id": "nec_phs", "log_id": "2017-05-06 16:54:29.313000", "file_name": "nec_phs_visit_occurrence_datasprint_2.csv", "message": null, "parsing": true}, {"received": true, "loading": true, "table_name": "procedure_occurrence", "hpo_id": "nec_phs", "log_id": "2017-05-06 16:53:55.510000", "file_name": "nec_phs_procedure_occurrence_datasprint_2.csv", "message": null, "parsing": true}, {"received": true, "loading": true, "table_name": "person", "hpo_id": "nec_phs", "log_id": "2017-05-06 16:53:54.140000", "file_name": "nec_phs_person_datasprint_2.csv", "message": null, "parsing": true}, {"received": true, "loading": true, "table_name": "measurement", "hpo_id": "nec_phs", "log_id": "2017-05-06 16:53:53.637000", "file_name": "nec_phs_measurement_datasprint_2.csv", "message": null, "parsing": true}, {"received": true, "loading": true, "table_name": "drug_exposure", "hpo_id": "nec_phs", "log_id": "2017-05-06 16:53:03.437000", "file_name": "nec_phs_drug_exposure_datasprint_2.csv", "message": null, "parsing": true}]